openetl_csdk/connectors/api/freshdesk.py
openetl_csdk/connectors/api/gsheet.py
openetl_csdk/connectors/api/hubspot.py
openetl_csdk/connectors/api/odoo.py
openetl_csdk/connectors/api/salesforce.py
openetl_csdk/connectors/database/mariadb.py
openetl_csdk/connectors/database/mysql.py
openetl_csdk/connectors/database/postgresql.py
openetl_csdk/connectors/database/snowflake.py
openetl_csdk/connectors/database/sqlserver.py
openetl_csdk/connectors/storage/s3.py
openetl_utils/__init__.py
openetl_utils/cache.py
openetl_utils/connector_utils.py
openetl_utils/encrypted_fields.py
openetl_utils/enums.py
openetl_utils/local_connection_utils.py
openetl_utils/logger.py
openetl_utils/main_api_class.py
openetl_utils/main_db_class.py
openetl_utils/main_storage_class.py
openetl_sdk-0.0.4.dist-info/METADATA
openetl_sdk-0.0.4.dist-info/WHEEL
openetl_sdk-0.0.4.dist-info/licenses/LICENSE
openetl_sdk-0.0.4.dist-info/RECORD
