Metadata-Version: 2.4
Name: openetl-sdk
Version: 0.0.4
Summary: OpenETL backend lib with connectors.
License: MIT
License-File: LICENSE
Keywords: etl,data,utilities,openetl,openetl-sdk,openetl-utils,openetl-csdk,openetl-connector-sdk
Author: Rusab Khan
Author-email: rusabkhan7@gmail.com
Requires-Python: >=3.12
Classifier: License :: OSI Approved :: MIT License
Classifier: Operating System :: OS Independent
Classifier: Programming Language :: Python :: 3
Classifier: Programming Language :: Python :: 3.12
Classifier: Programming Language :: Python :: 3.13
Classifier: Programming Language :: Python :: 3.14
Requires-Dist: SQLAlchemy (==2.0.36)
Requires-Dist: alembic (==1.14.0)
Requires-Dist: croniter (==5.0.1)
Requires-Dist: cryptography (==43.0.3)
Requires-Dist: flatten-json (==0.1.14)
Requires-Dist: numpy (==2.1.3)
Requires-Dist: pandas (==2.2.3)
Requires-Dist: regex (==2024.11.6)
Requires-Dist: requests (==2.32.3)
Requires-Dist: setuptools (==75.6.0)
Project-URL: Documentation, https://rusabkhan.github.io/OpenETL/
Project-URL: Homepage, https://dataomnisolutions.com
Project-URL: Repository, https://github.com/RusabKhan/OpenETL
